lowtime-0.3.0.dist-info/METADATA
lowtime-0.3.0.dist-info/WHEEL
lowtime-0.3.0.dist-info/licenses/LICENSE
lowtime/exceptions.py
lowtime/graph_utils.py
lowtime/solver.py
lowtime/py.typed
lowtime/cost_model.py
lowtime/_lowtime_rs.pyi
lowtime/__init__.py
lowtime/perseus/visualizer.py
lowtime/perseus/__init__.py
lowtime/perseus/instruction.py
lowtime/perseus/schedule.py
lowtime/operation.py
lowtime/_lowtime_rs.cpython-310-arm-linux-gnueabihf.so
lowtime-0.3.0.dist-info/RECORD
